{
    "uvs":[],
    "materials":[{
        "DbgIndex":7,
        "wireframe":false,
        "colorDiffuse":[0.017919,0.100055,0.64],
        "blending":"NormalBlending",
        "opacity":1,
        "colorEmissive":[0,0,0],
        "visible":true,
        "DbgColor":15658734,
        "shading":"phong",
        "transparent":false,
        "DbgName":"Dark Blue",
        "depthTest":true,
        "colorSpecular":[0.5,0.5,0.5],
        "specularCoef":50,
        "depthWrite":true
    },{
        "DbgIndex":0,
        "wireframe":false,
        "colorDiffuse":[0.64,0.64,0.64],
        "blending":"NormalBlending",
        "opacity":1,
        "colorEmissive":[0,0,0],
        "visible":true,
        "DbgColor":15658734,
        "shading":"lambert",
        "transparent":false,
        "DbgName":"White",
        "depthTest":true,
        "depthWrite":true
    },{
        "DbgIndex":4,
        "wireframe":false,
        "colorDiffuse":[0.012997,0.64,0],
        "blending":"NormalBlending",
        "opacity":1,
        "colorEmissive":[0,0,0],
        "visible":true,
        "DbgColor":15658496,
        "shading":"phong",
        "transparent":false,
        "DbgName":"Green",
        "depthTest":true,
        "colorSpecular":[0.5,0.5,0.5],
        "specularCoef":50,
        "depthWrite":true
    },{
        "DbgIndex":3,
        "wireframe":false,
        "colorDiffuse":[0.239778,0.056242,0.8],
        "blending":"NormalBlending",
        "opacity":1,
        "colorEmissive":[0,0,0],
        "visible":true,
        "DbgColor":238,
        "shading":"phong",
        "transparent":false,
        "DbgName":"Purple",
        "depthTest":true,
        "colorSpecular":[0.5,0.5,0.5],
        "specularCoef":50,
        "depthWrite":true
    },{
        "DbgIndex":2,
        "wireframe":false,
        "colorDiffuse":[0.64,0.206362,0.010513],
        "blending":"NormalBlending",
        "opacity":1,
        "colorEmissive":[0,0,0],
        "visible":true,
        "DbgColor":60928,
        "shading":"phong",
        "transparent":false,
        "DbgName":"Orange",
        "depthTest":true,
        "colorSpecular":[0.5,0.5,0.5],
        "specularCoef":50,
        "depthWrite":true
    },{
        "DbgIndex":6,
        "wireframe":false,
        "colorDiffuse":[0,0,0],
        "blending":"NormalBlending",
        "opacity":1,
        "colorEmissive":[0,0,0],
        "visible":true,
        "DbgColor":15597806,
        "shading":"phong",
        "transparent":false,
        "DbgName":"Black",
        "depthTest":true,
        "colorSpecular":[0.5,0.5,0.5],
        "specularCoef":50,
        "depthWrite":true
    },{
        "DbgIndex":1,
        "wireframe":false,
        "colorDiffuse":[0.64,0.02185,0.030376],
        "blending":"NormalBlending",
        "opacity":1,
        "colorEmissive":[0,0,0],
        "visible":true,
        "DbgColor":15597568,
        "shading":"phong",
        "transparent":false,
        "DbgName":"Red",
        "depthTest":true,
        "colorSpecular":[0.5,0.5,0.5],
        "specularCoef":50,
        "depthWrite":true
    },{
        "DbgIndex":5,
        "wireframe":false,
        "colorDiffuse":[0.044076,0.518111,0.64],
        "blending":"NormalBlending",
        "opacity":1,
        "colorEmissive":[0,0,0],
        "visible":true,
        "DbgColor":61166,
        "shading":"phong",
        "transparent":false,
        "DbgName":"Light Blue",
        "depthTest":true,
        "colorSpecular":[0.5,0.5,0.5],
        "specularCoef":50,
        "depthWrite":true
    }],
    "metadata":{
        "uvs":0,
        "materials":8,
        "version":3,
        "vertices":726,
        "faces":696,
        "generator":"io_three",
        "normals":239,
        "type":"Geometry"
    },
    "vertices":[8,0,-8,8,0,8,-8,0,8,-8,0,-8,8,16,-8,8,16,8,-8,16,8,-8,16,-8,8,0,-6,8,0,-4,8,0,-2,8,0,0,8,0,2,8,0,4,8,0,6,6,0,-8,4,0,-8,2,0,-8,2e-06,0,-8,-2,0,-8,-4,0,-8,-6,0,-8,8,2,-8,8,4,-8,8,6,-8,8,8,-8,8,10,-8,8,12,-8,8,14,-8,6,0,8,4,0,8,2,0,8,-0,0,8,-2,0,8,-4,0,8,-6,0,8,8,2,8,8,4,8,8,6,8,8,8,8,8,10,8,8,12,8,8,14,8,-8,0,6,-8,0,4,-8,0,2,-8,0,-2e-06,-8,0,-2,-8,0,-4,-8,0,-6,-8,2,8,-8,4,8,-8,6,8,-8,8,8,-8,10,8,-8,12,8,-8,14,8,-8,2,-8,-8,4,-8,-8,6,-8,-8,8,-8,-8,10,-8,-8,12,-8,-8,14,-8,8,16,-6,8,16,-4,8,16,-2,8,16,4e-06,8,16,2,8,16,4,8,16,6,6,16,-8,4,16,-8,2,16,-8,2e-06,16,-8,-2,16,-8,-4,16,-8,-6,16,-8,6,16,8,4,16,8,2,16,8,-4e-06,16,8,-2,16,8,-4,16,8,-6,16,8,-8,16,6,-8,16,4,-8,16,2,-8,16,-2e-06,-8,16,-2,-8,16,-4,-8,16,-6,6,14,-8,6,12,-8,6,10,-8,6,8,-8,6,6,-8,6,4,-8,6,2,-8,4,14,-8,4,12,-8,4,10,-8,4,8,-8,4,6,-8,4,4,-8,4,2,-8,2,14,-8,2,12,-8,2,10,-8,2,8,-8,2,6,-8,2,4,-8,2,2,-8,2e-06,14,-8,2e-06,12,-8,2e-06,10,-8,8,7,-2,2e-06,6,-8,2e-06,4,-8,2e-06,2,-8,-2,14,-8,-2,12,-8,-2,10,-8,-2,8,-8,-2,6,-8,-2,4,-8,-2,2,-8,-4,14,-8,-4,12,-8,-4,10,-8,-4,8,-8,-4,6,-8,-4,4,-8,-4,2,-8,-6,14,-8,-6,12,-8,-6,10,-8,-6,8,-8,-6,6,-8,-6,4,-8,-6,2,-8,-8,2,6,-8,4,6,-8,6,6,-8,8,6,-8,10,6,-8,12,6,-8,14,6,-8,2,4,-8,4,4,-8,6,4,-8,8,4,-8,10,4,-8,12,4,-8,14,4,-8,2,2,-8,4,2,-8,6,2,-8,8,2,-8,10,2,-8,12,2,-8,14,2,-8,2,-2e-06,-8,4,-2e-06,-8,6,-2e-06,2,9,-8,-8,10,-2e-06,-8,12,-2e-06,-8,14,-2e-06,-8,2,-2,-8,4,-2,-8,6,-2,-8,8,-2,-8,10,-2,-8,12,-2,-8,14,-2,-8,2,-4,-8,4,-4,-8,6,-4,-8,8,-4,-8,10,-4,-8,12,-4,-8,14,-4,-8,2,-6,-8,4,-6,-8,6,-6,-8,8,-6,-8,10,-6,-8,12,-6,-8,14,-6,6,2,8,6,4,8,6,6,8,6,8,8,6,10,8,6,12,8,6,14,8,4,2,8,4,4,8,4,6,8,4,8,8,4,10,8,4,12,8,4,14,8,2,2,8,2,4,8,2,6,8,2,8,8,2,10,8,2,12,8,2,14,8,-1e-06,2,8,-1e-06,4,8,-2e-06,6,8,-3e-06,10,8,-3e-06,12,8,-4e-06,14,8,-2,2,8,-2,4,8,-2,6,8,-2,8,8,-2,10,8,-2,12,8,-2,14,8,-4,2,8,-4,4,8,-4,6,8,-4,8,8,-4,10,8,-4,12,8,-4,14,8,-6,2,8,-6,4,8,-6,6,8,-6,8,8,-6,10,8,-6,12,8,-6,14,8,8,2,-6,8,4,-6,8,6,-6,8,8,-6,8,10,-6,8,12,-6,8,14,-6,8,2,-4,8,4,-4,8,6,-4,8,8,-4,8,10,-4,8,12,-4,8,14,-4,8,2,-2,8,4,-2,8,6,-2,8,8,-2,8,10,-2,8,12,-2,8,14,-2,8,2,1e-06,8,4,1e-06,8,6,2e-06,2,0,-1,8,10,2e-06,8,12,3e-06,8,14,3e-06,8,2,2,8,4,2,8,6,2,8,8,2,8,10,2,8,12,2,8,14,2,8,2,4,8,4,4,8,6,4,8,8,4,8,10,4,8,12,4,8,14,4,8,2,6,8,4,6,8,6,6,8,8,6,8,10,6,8,12,6,8,14,6,6,16,-6,4,16,-6,2,16,-6,1e-06,16,-6,-2,16,-6,-4,16,-6,-6,16,-6,6,16,-4,4,16,-4,2,16,-4,1e-06,16,-4,-2,16,-4,-4,16,-4,-6,16,-4,6,16,-2,4,16,-2,2,16,-2,-0,16,-2,-2,16,-2,-4,16,-2,-6,16,-2,6,16,3e-06,4,16,2e-06,2,16,1e-06,-1,15,0,-2,16,-0,-4,16,-1e-06,-6,16,-2e-06,6,16,2,4,16,2,2,16,2,-2e-06,16,2,-2,16,2,-4,16,2,-6,16,2,6,16,4,4,16,4,2,16,4,-3e-06,16,4,-2,16,4,-4,16,4,-6,16,4,6,16,6,4,16,6,2,16,6,-4e-06,16,6,-2,16,6,-4,16,6,-6,16,6,6,0,-6,6,0,-4,6,0,-2,6,0,0,6,0,2,6,0,4,6,0,6,4,0,-6,4,0,-4,4,0,-2,4,0,0,4,0,2,4,0,4,4,0,6,2,0,-6,2,0,-4,2,0,-2,2,0,0,2,0,2,2,0,4,2,0,6,1e-06,0,-6,1e-06,0,-4,1e-06,0,-2,0,0,2,0,0,4,-0,0,6,-2,0,-6,-2,0,-4,-2,0,-2,-2,0,-1e-06,-2,0,2,-2,0,4,-2,0,6,-4,0,-6,-4,0,-4,-4,0,-2,-4,0,-1e-06,-4,0,2,-4,0,4,-4,0,6,-6,0,-6,-6,0,-4,-6,0,-2,-6,0,-1e-06,-6,0,2,-6,0,4,-6,0,6,-8,7,2,-8,9,2,-8,7,-2e-06,-8,9,-2e-06,-8,7,-2,-8,9,-2,-8,6,0.999998,-8,8,0.999998,-8,10,0.999998,-8,6,-1,-8,8,-1,-8,10,-1,-8,9,-1,-8,7,-1,-8,9,0.999998,-8,7,0.999998,-7,6,2,-7,8,2,-7,10,2,-7,6,-2e-06,-7,10,-2e-06,-7,6,-2,-7,8,-2,-7,10,-2,-7,7,2,-7,9,2,-7,7,-2e-06,-7,9,-2e-06,-7,7,-2,-7,9,-2,-7,6,0.999998,-7,8,0.999998,-7,10,0.999998,-7,6,-1,-7,8,-1,-7,10,-1,-7,9,-1,-7,7,-1,-7,9,0.999998,-7,7,0.999998,-9,8,-2e-06,-9,7,-2e-06,-9,9,-2e-06,-9,8,0.999998,-9,8,-1,-9,9,-1,-9,7,-1,-9,9,0.999998,-9,7,0.999998,2,7,-8,2e-06,9,-8,2e-06,7,-8,-2,9,-8,-2,7,-8,1,10,-8,1,8,-8,1,6,-8,-0.999998,10,-8,-0.999998,8,-8,-0.999998,6,-8,-0.999998,7,-8,-0.999998,9,-8,1,7,-8,1,9,-8,2,10,-8,2,8,-8,2,6,-8,2e-06,10,-8,2e-06,6,-8,-2,10,-8,-2,8,-8,-2,6,-8,2,9,-8,2,7,-8,2e-06,9,-8,2e-06,7,-8,-2,9,-8,-2,7,-8,1,10,-8,1,8,-8,1,6,-8,-0.999998,10,-8,-0.999998,8,-8,-0.999998,6,-8,-0.999998,7,-8,-0.999998,9,-8,1,7,-8,1,9,-8,2,10,-7,2,8,-7,2,6,-7,2e-06,10,-7,2e-06,6,-7,-2,10,-7,-2,8,-7,-2,6,-7,2,9,-7,2,7,-7,2e-06,9,-7,2e-06,7,-7,-2,9,-7,-2,7,-7,1,10,-7,1,8,-7,1,6,-7,-0.999998,10,-7,-0.999998,8,-7,-0.999998,6,-7,-0.999998,7,-7,-0.999998,9,-7,1,7,-7,1,9,-7,2e-06,8,-9,2e-06,9,-9,2e-06,7,-9,1,8,-9,-0.999998,8,-9,-0.999998,7,-9,-0.999998,9,-9,1,7,-9,1,9,-9,8,9,-2,8,7,2e-06,8,9,2e-06,8,7,2,8,9,2,8,6,-0.999998,8,8,-0.999998,8,10,-0.999998,8,6,1,8,8,1,8,10,1,8,9,1,8,7,1,8,9,-0.999998,8,7,-0.999998,7,7,-2,7,6,-2,7,8,-2,7,10,-2,7,6,2e-06,7,10,2e-06,7,6,2,7,8,2,7,10,2,7,9,-2,7,7,2e-06,7,9,2e-06,7,7,2,7,9,2,7,6,-0.999998,7,8,-0.999998,7,10,-0.999998,7,6,1,7,8,1,7,10,1,7,9,1,7,7,1,7,9,-0.999998,7,7,-0.999998,9,8,2e-06,9,7,2e-06,9,9,2e-06,9,8,-0.999998,9,8,1,9,9,1,9,7,1,9,9,-0.999998,9,7,-0.999998,2,0,1,1e-06,0,-1,0,0,0.999999,-2,0,-1,-2,0,0.999999,1,0,-2,1,0,-0,1,0,2,-0.999999,0,-2,-0.999999,0,-1e-06,-1,0,2,-1,0,0.999999,-0.999999,0,-1,1,0,1,1,0,-1,2,0,-1,2,0,-2,2,0,0,2,0,2,1e-06,0,-2,0,0,2,-2,0,-2,-2,0,-1e-06,-2,0,2,2,0,1,1e-06,0,-1,0,0,0.999999,-2,0,-1,-2,0,0.999999,1,0,-2,1,0,-0,1,0,2,-0.999999,0,-2,-0.999999,0,-1e-06,-1,0,2,-1,0,0.999999,-0.999999,0,-1,1,0,1,1,0,-1,2,1,-1,2,1,-2,2,1,-0,2,1,2,1e-06,1,-2,0,1,2,-2,1,-2,-2,1,-1e-06,-2,1,2,2,1,1,1e-06,1,-1,0,1,0.999999,-2,1,-1,-2,1,0.999999,1,1,-2,1,1,-1e-06,1,1,2,-0.999999,1,-2,-0.999999,1,-1e-06,-1,1,2,-1,1,0.999999,-0.999999,1,-1,1,1,0.999999,1,1,-1,1e-06,-1,-1e-06,1e-06,-1,-1,0,-1,0.999999,1,-1,-0,-0.999999,-1,-1e-06,-1,-1,0.999999,-0.999999,-1,-1,1,-1,1,1,-1,-1,0.999999,15,1e-06,-1e-06,15,1,-1e-06,15,-0.999999,0.999998,15,2,-2,15,1,-1,15,-2,2,15,-0.999999,2,15,1,1,15,-2,-2,15,-1,-1,15,2,-1,15,-1,0.999999,15,-0.999999,0.999999,15,1,-1,15,1,-2,15,2,2,15,2,-2,15,-2,2,15,-2,-1,16,1,0.999999,16,1,0.999999,16,-0.999999,-1,16,-1,-1,16,2,-2,16,-1,1,16,-2,2,16,1,2,16,-0.999999,-1,16,-2,-2,16,1,0.999998,16,2,-1e-06,16,-0.999999,-1e-06,16,1,0.999999,16,1e-06,-1,16,0,2,7,8,-2e-06,16,2,-2,16,-0,-0,16,-2,2,16,1e-06,-2e-06,15,2,-2,15,-0,-0,15,-2,2,15,1e-06,-1,17,1,0.999999,17,1,0.999999,17,-0.999999,-1,17,-1,-1e-06,17,-0.999999,-1e-06,17,1,0.999999,17,1e-06,-1,17,0,-1e-06,17,1e-06,2,9,8,-2e-06,7,8,-2e-06,9,8,-2,7,8,-2,9,8,0.999998,6,8,0.999998,8,8,0.999997,10,8,-1,6,8,-1,8,8,-1,10,8,-1,9,8,-1,7,8,0.999997,9,8,0.999998,7,8,2,6,7,2,8,7,2,10,7,-2e-06,6,7,-2e-06,10,7,-2,6,7,-2,8,7,-2,10,7,2,7,7,2,9,7,-2e-06,7,7,-2e-06,9,7,-2,7,7,-2,9,7,0.999998,6,7,0.999998,8,7,0.999997,10,7,-1,6,7,-1,8,7,-1,10,7,-1,9,7,-1,7,7,0.999998,9,7,0.999998,7,7,-2e-06,8,9,-2e-06,7,9,-3e-06,9,9,0.999997,8,9,-1,8,9,-1,9,9,-1,7,9,0.999997,9,9,0.999998,7,9],
    "normals":[0,1,0,0,-1,0,-1,-0,-1e-06,0,0,-1,1,0,0,-0,-0,1,-0,-0,1,-0,-0,1,0,-0,1,-0,-0,1,-1e-06,-0,1,-0,-0,1,-0,0,1,-0,-0,1,-0,-0,1,-0,-0,1,-0,0,1,-0,-0,1,-0,0,1,-0,-0,1,-0,-0,1,-0,-0,1,-0,0,1,-0,-0,1,-0,0,1,-0,-0,1,-0,-0,1,0,-0,1,-0,-0,1,-0,0,1,-1,0,0,0,0,0,-0,-0,1,-0,-0,1,-0,-0,1,-1e-06,-0,1,-0,-0,1,-0,-0,1,0,0,1,0,-0,1,0,-0,1,-1e-06,-0,1,-1e-06,-0,1,-1e-06,-0,1,-1e-06,-0,1,-1e-06,-0,1,1,0,0,1,0,0,1,0,0,1,0,1e-06,1,0,0,1,0,0,1,0,0,1,0,0,1,0,0,1,0,0,1,0,1e-06,1,0,1e-06,1,0,0,1,0,0,1,0,0,1,0,0,1,0,0,1,-0,0,0,0,-1,-0,-1,0,1,0,0,0,0,-1,1,0,0,1,0,1e-06,1,0,0,1,0,-0,1,0,0,1,0,0,1,0,0,1,0,0,1,0,0,1,0,0,1,0,0,1,0,0,1,0,0,0,0,-1,1e-06,0,-1,0,0,-1,1e-06,0,-1,0,0,-1,0,0,-1,0,0,-1,0,0,-1,1e-06,1e-06,-1,0,0,-1,0,0,-1,1e-06,0,-1,0,-0,-1,0,0,-1,1e-06,0,-1,1e-06,0,-1,0,0,-1,0,0,-1,1e-06,0,-1,0,0,-1,0,0,-1,1e-06,0,-1,0,-0,-1,-1,-0,-0,1e-06,0,-1,0,0,-1,0,-0,-1,0,0,-1,0,1,-0,0,0,-1,0,-0,-1,0,-0,-1,1e-06,0,-1,0,0,-1,0,-0,-1,0,-0,-1,0,-0,-1,0,0,-1,0,-0,-1,0,-0,-1,0,0,-1,0,0,-1,0,-0,-1,0,-0,-1,-1,0,-1e-06,-1,0,-0,-1,0,-1e-06,-1,0,-0,-1,-0,-1e-06,-1,0,-0,-1,-0,-0,-1,-0,0,-1,0,-0,-1,0,-1e-06,-1,0,-1e-06,-1,0,-0,-1,0,-1e-06,-1,0,-0,-1,0,-1e-06,-1,0,-1e-06,-1,0,-0,-1,0,-0,-1,0,-0,0,-0,1,-1,-0,-1e-06,-1,-0,-0,-1,0,-0,-0,1,0,-1,-0,-0,-1,-0,-1e-06,-1,-0,-0,-1,-0,-0,-1,-0,-0,-1,-0,-0,-1,-0,-0,-1,-0,-0,-1,-0,0,-1,-0,0,-1,-0,0,-1,-0,-0,-1,-0,-0,-1,-0,-0,-1,-0,0,-1,-0,-0,-1,-0,-0,-1,-0,-0,-1,-0,-0,-1,-0,-1e-06,0,-1,-0,-1,-0,-0,-1e-06,0,1,1,0,0,-0,0,1,0,1,-0,0,1,-0,-1,-0,-0,0,1,-0,0,1,-0,0,1,-0,0,1,-0,0,1,-0,-0,0,-1,0,-0,1,0,0,1,-1,0,0,-1e-06,-0,1,-0,-0,1,-0,-0,1,-0,-0,1,1,-0,0,1,-0,0,-0,-0,1,-0,-0,1,-1e-06,0,1,0,-0,1,-1,0,-0,-1,0,-0,-1,0,-0,-1,0,-0,0,0,-1,0,-0,-1,-0,0,1,1,0,0,0,0,-1,-1,0,-0,-0,0,1,0,0,-1,-0,0,1,0,0,-1,1,0,0,-1,0,-0,0,-0,-1,1,0,0,1,0,0,-1,-0,-0,0,0,-1,-1,-0,-0,-0,0,1,-0,0,1,0,0,-1,1,0,0,-1,-0,-0,-1,0,-0,-0,0,1,-1,0,-0,1,0,0,1,0,0,-1,0,-0,1,0,0,-1,-0,-0,1,0,0,0,0,-1,0,0,-1,0,0,-1,-1,-0,-0,-1,-0,-0,1,0,0,1,0,0],
    "faces":[35,383,43,2,35,0,0,0,0,0,35,335,84,6,85,1,1,1,1,1,35,286,42,5,70,1,2,2,2,2,35,237,56,6,84,1,3,3,3,3,35,189,63,7,91,1,4,4,4,4,35,140,57,3,21,1,5,5,5,5,35,15,0,22,98,1,6,6,6,6,35,98,105,16,15,1,7,7,7,7,35,105,112,17,16,1,8,8,8,8,35,112,119,18,17,1,9,9,9,9,35,119,126,19,18,1,10,10,10,10,35,126,133,20,19,1,8,8,8,8,35,133,140,21,20,1,8,8,8,8,35,4,71,92,28,1,11,11,11,11,35,28,92,93,27,1,12,12,12,12,35,27,93,94,26,1,13,13,13,13,35,26,94,95,25,1,13,13,13,13,35,25,95,96,24,1,14,14,14,14,35,24,96,97,23,1,15,15,15,15,35,23,97,98,22,1,16,16,16,16,35,71,72,99,92,1,17,17,17,17,35,92,99,100,93,1,18,18,18,18,35,93,100,101,94,1,19,19,19,19,35,94,101,102,95,1,20,20,20,20,35,95,102,103,96,1,6,6,6,6,35,96,103,104,97,1,21,21,21,21,35,97,104,105,98,1,22,22,22,22,35,72,73,106,99,1,23,23,23,23,35,99,106,107,100,1,24,24,24,24,35,100,107,108,101,1,17,17,17,17,35,115,114,121,122,1,25,25,25,25,35,108,107,114,115,1,26,26,26,26,35,103,110,111,104,1,27,27,27,27,35,104,111,112,105,1,8,8,8,8,35,73,74,113,106,1,28,28,28,28,35,106,113,114,107,1,29,29,29,29,35,102,101,108,109,1,19,19,19,19,35,446,439,499,503,1,30,30,30,30,35,124,443,467,455,1,31,31,31,31,35,103,102,109,110,1,32,32,32,32,35,111,118,119,112,1,8,8,8,8,35,74,75,120,113,1,23,23,23,23,35,113,120,121,114,1,33,33,33,33,35,111,110,117,118,1,34,34,34,34,35,165,108,448,456,1,31,31,31,31,35,108,438,462,448,1,31,31,31,31,35,118,117,124,125,1,19,19,19,19,35,118,125,126,119,1,35,35,35,35,35,75,76,127,120,1,23,23,23,23,35,120,127,128,121,1,36,36,36,36,35,121,128,129,122,1,37,37,37,37,35,131,124,123,130,1,38,38,38,38,35,130,123,122,129,1,38,38,38,38,35,124,131,132,125,1,39,39,39,39,35,125,132,133,126,1,40,40,40,40,35,76,77,134,127,1,37,37,37,37,35,127,134,135,128,1,8,8,8,8,35,128,135,136,129,1,8,8,8,8,35,129,136,137,130,1,8,8,8,8,35,130,137,138,131,1,8,8,8,8,35,131,138,139,132,1,39,39,39,39,35,132,139,140,133,1,40,40,40,40,35,77,7,63,134,1,8,8,8,8,35,134,63,62,135,1,26,26,26,26,35,135,62,61,136,1,41,41,41,41,35,136,61,60,137,1,42,42,42,42,35,137,60,59,138,1,43,43,43,43,35,138,59,58,139,1,44,44,44,44,35,139,58,57,140,1,45,45,45,45,35,56,147,85,6,1,46,46,46,46,35,147,154,86,85,1,47,47,47,47,35,154,161,87,86,1,48,48,48,48,35,161,168,88,87,1,48,48,48,48,35,168,175,89,88,1,49,49,49,49,35,175,182,90,89,1,50,50,50,50,35,182,189,91,90,1,48,48,48,48,35,2,43,141,50,1,51,51,51,51,35,50,141,142,51,1,52,52,52,52,35,51,142,143,52,1,53,53,53,53,35,52,143,144,53,1,54,54,54,54,35,53,144,145,54,1,46,46,46,46,35,54,145,146,55,1,48,48,48,48,35,55,146,147,56,1,48,48,48,48,35,43,44,148,141,1,55,55,55,55,35,141,148,149,142,1,48,48,48,48,35,142,149,150,143,1,48,48,48,48,35,143,150,151,144,1,50,50,50,50,35,144,151,152,145,1,56,56,56,56,35,145,152,153,146,1,57,57,57,57,35,146,153,154,147,1,58,58,58,58,35,44,45,155,148,1,59,59,59,59,35,148,155,156,149,1,60,60,60,60,35,149,156,157,150,1,48,48,48,48,35,160,159,166,167,1,46,46,46,46,35,167,166,173,174,1,61,61,61,61,35,152,159,160,153,1,46,46,46,46,35,153,160,161,154,1,46,46,46,46,35,45,46,162,155,1,50,50,50,50,35,155,162,163,156,1,62,62,62,62,35,180,173,172,179,1,63,63,63,63,35,398,391,427,431,1,64,64,64,64,35,157,390,414,400,1,65,65,65,65,35,179,172,171,178,1,66,66,66,66,35,160,167,168,161,1,46,46,46,46,35,46,47,169,162,1,62,62,62,62,35,162,169,170,163,1,61,61,61,61,35,164,163,170,171,1,47,47,47,47,35,387,396,420,411,1,65,65,65,65,35,172,389,413,406,1,67,67,67,67,35,157,156,163,164,1,68,68,68,68,35,167,174,175,168,1,69,69,69,69,35,47,48,176,169,1,59,59,59,59,35,169,176,177,170,1,70,70,70,70,35,170,177,178,171,1,59,59,59,59,35,151,150,157,158,1,71,71,71,71,35,152,151,158,159,1,71,71,71,71,35,173,180,181,174,1,66,66,66,66,35,174,181,182,175,1,72,72,72,72,35,48,49,183,176,1,50,50,50,50,35,176,183,184,177,1,50,50,50,50,35,177,184,185,178,1,73,73,73,73,35,178,185,186,179,1,72,72,72,72,35,179,186,187,180,1,48,48,48,48,35,180,187,188,181,1,74,74,74,74,35,181,188,189,182,1,74,74,74,74,35,49,3,57,183,1,75,75,75,75,35,183,57,58,184,1,74,74,74,74,35,184,58,59,185,1,76,76,76,76,35,185,59,60,186,1,77,77,77,77,35,186,60,61,187,1,78,78,78,78,35,187,61,62,188,1,79,79,79,79,35,188,62,63,189,1,80,80,80,80,35,42,196,78,5,1,81,81,81,81,35,196,203,79,78,1,82,82,82,82,35,203,210,80,79,1,83,83,83,83,35,210,216,81,80,1,84,84,84,84,35,216,223,82,81,1,85,85,85,85,35,223,230,83,82,1,86,86,86,86,35,230,237,84,83,1,87,87,87,87,35,1,29,190,36,1,88,88,88,88,35,36,190,191,37,1,89,89,89,89,35,37,191,192,38,1,90,90,90,90,35,38,192,193,39,1,91,91,91,91,35,39,193,194,40,1,92,92,92,92,35,40,194,195,41,1,92,92,92,92,35,41,195,196,42,1,81,81,81,81,35,29,30,197,190,1,93,93,93,93,35,190,197,198,191,1,94,94,94,94,35,191,198,199,192,1,95,95,95,95,35,192,199,200,193,1,96,96,96,96,35,193,200,201,194,1,97,97,97,97,35,194,201,202,195,1,98,98,98,98,35,195,202,203,196,1,99,99,99,99,35,30,31,204,197,1,93,93,93,93,35,197,204,205,198,1,93,93,93,93,35,198,205,206,199,1,93,93,93,93,35,209,208,214,215,1,100,100,100,100,35,215,214,221,222,1,101,101,101,101,35,201,208,209,202,1,102,102,102,102,35,202,209,210,203,1,98,98,98,98,35,31,32,211,204,1,93,93,93,93,35,204,211,212,205,1,103,103,103,103,35,228,221,220,227,1,64,64,64,64,35,691,684,720,724,1,104,104,104,104,35,678,207,694,702,1,50,50,50,50,35,227,220,219,226,1,64,64,64,64,35,209,215,216,210,1,105,105,105,105,35,32,33,217,211,1,106,106,106,106,35,211,217,218,212,1,107,107,107,107,35,213,212,218,219,1,108,108,108,108,35,688,214,697,712,1,109,109,109,109,35,691,680,704,715,1,1,1,1,1,35,206,205,212,213,1,110,110,110,110,35,215,222,223,216,1,111,111,111,111,35,33,34,224,217,1,93,93,93,93,35,217,224,225,218,1,112,112,112,112,35,218,225,226,219,1,93,93,93,93,35,200,199,206,207,1,94,94,94,94,35,201,200,207,208,1,113,113,113,113,35,221,228,229,222,1,114,114,114,114,35,222,229,230,223,1,115,115,115,115,35,34,35,231,224,1,93,93,93,93,35,224,231,232,225,1,112,112,112,112,35,225,232,233,226,1,93,93,93,93,35,226,233,234,227,1,93,93,93,93,35,227,234,235,228,1,93,93,93,93,35,228,235,236,229,1,116,116,116,116,35,229,236,237,230,1,117,117,117,117,35,35,2,50,231,1,118,118,118,118,35,231,50,51,232,1,119,119,119,119,35,232,51,52,233,1,120,120,120,120,35,233,52,53,234,1,121,121,121,121,35,234,53,54,235,1,122,122,122,122,35,235,54,55,236,1,123,123,123,123,35,236,55,56,237,1,124,124,124,124,35,28,244,64,4,1,125,125,125,125,35,244,251,65,64,1,126,126,126,126,35,251,258,66,65,1,127,127,127,127,35,258,265,67,66,1,128,128,128,128,35,265,272,68,67,1,129,129,129,129,35,272,279,69,68,1,130,130,130,130,35,279,286,70,69,1,131,131,131,131,35,0,8,238,22,1,132,132,132,132,35,22,238,239,23,1,133,133,133,133,35,23,239,240,24,1,134,134,134,134,35,24,240,241,25,1,135,135,135,135,35,25,241,242,26,1,133,133,133,133,35,26,242,243,27,1,136,136,136,136,35,27,243,244,28,1,137,137,137,137,35,8,9,245,238,1,132,132,132,132,35,238,245,246,239,1,132,132,132,132,35,239,246,247,240,1,132,132,132,132,35,240,247,248,241,1,138,138,138,138,35,241,248,249,242,1,139,139,139,139,35,242,249,250,243,1,140,140,140,140,35,243,250,251,244,1,141,141,141,141,35,9,10,252,245,1,132,132,132,132,35,245,252,253,246,1,132,132,132,132,35,246,253,254,247,1,132,132,132,132,35,248,247,254,255,1,142,142,142,142,35,249,248,255,256,1,142,142,142,142,35,249,256,257,250,1,143,143,143,143,35,250,257,258,251,1,125,125,125,125,35,10,11,259,252,1,132,132,132,132,35,252,259,260,253,1,132,132,132,132,35,257,256,263,264,1,142,142,142,142,35,518,511,547,551,1,144,144,144,144,35,255,116,520,522,1,67,67,67,67,35,264,263,270,271,1,145,145,145,145,35,257,264,265,258,1,132,132,132,132,35,11,12,266,259,1,132,132,132,132,35,259,266,267,260,1,146,146,146,146,35,277,270,269,276,1,147,147,147,147,35,515,263,525,539,1,148,148,148,148,35,511,518,542,535,1,144,144,144,144,35,276,269,268,275,1,149,149,149,149,35,264,271,272,265,1,150,150,150,150,35,12,13,273,266,1,151,151,151,151,35,266,273,274,267,1,152,152,152,152,35,267,274,275,268,1,153,153,153,153,35,261,260,267,268,1,154,154,154,154,35,254,253,260,261,1,142,142,142,142,35,270,277,278,271,1,155,155,155,155,35,271,278,279,272,1,156,156,156,156,35,13,14,280,273,1,157,157,157,157,35,273,280,281,274,1,158,158,158,158,35,274,281,282,275,1,159,159,159,159,35,275,282,283,276,1,159,159,159,159,35,276,283,284,277,1,160,160,160,160,35,277,284,285,278,1,161,161,161,161,35,278,285,286,279,1,162,162,162,162,35,14,1,36,280,1,159,159,159,159,35,280,36,37,281,1,163,163,163,163,35,281,37,38,282,1,164,164,164,164,35,282,38,39,283,1,165,165,165,165,35,283,39,40,284,1,166,166,166,166,35,284,40,41,285,1,167,167,167,167,35,285,41,42,286,1,168,168,168,168,35,77,293,91,7,1,1,1,1,1,35,293,300,90,91,1,1,1,1,1,35,300,307,89,90,1,1,1,1,1,35,307,314,88,89,1,1,1,1,1,35,314,321,87,88,1,1,1,1,1,35,321,328,86,87,1,1,1,1,1,35,328,335,85,86,1,1,1,1,1,35,4,64,287,71,1,1,1,1,1,35,71,287,288,72,1,1,1,1,1,35,72,288,289,73,1,1,1,1,1,35,73,289,290,74,1,1,1,1,1,35,74,290,291,75,1,1,1,1,1,35,75,291,292,76,1,1,1,1,1,35,76,292,293,77,1,1,1,1,1,35,64,65,294,287,1,1,1,1,1,35,287,294,295,288,1,1,1,1,1,35,288,295,296,289,1,1,1,1,1,35,289,296,297,290,1,1,1,1,1,35,290,297,298,291,1,1,1,1,1,35,291,298,299,292,1,1,1,1,1,35,292,299,300,293,1,1,1,1,1,35,65,66,301,294,1,1,1,1,1,35,294,301,302,295,1,1,1,1,1,35,295,302,303,296,1,1,1,1,1,35,297,296,303,304,1,169,169,169,169,35,298,297,304,305,1,169,169,169,169,35,298,305,306,299,1,1,1,1,1,35,299,306,307,300,1,1,1,1,1,35,66,67,308,301,1,1,1,1,1,35,301,308,309,302,1,1,1,1,1,35,306,305,312,313,1,169,169,169,169,35,662,649,634,666,1,170,170,170,170,35,648,319,640,635,1,171,171,171,171,35,313,312,319,320,1,169,169,169,169,35,306,313,314,307,1,1,1,1,1,35,67,68,315,308,1,1,1,1,1,35,308,315,316,309,1,1,1,1,1,35,326,319,318,325,1,65,65,65,65,35,664,651,632,668,1,172,172,172,172,35,646,656,627,637,1,173,173,173,173,35,325,318,317,324,1,65,65,65,65,35,313,320,321,314,1,1,1,1,1,35,68,69,322,315,1,1,1,1,1,35,315,322,323,316,1,1,1,1,1,35,316,323,324,317,1,1,1,1,1,35,310,309,316,317,1,169,169,169,169,35,303,302,309,310,1,169,169,169,169,35,319,326,327,320,1,1,1,1,1,35,320,327,328,321,1,1,1,1,1,35,69,70,329,322,1,1,1,1,1,35,322,329,330,323,1,1,1,1,1,35,323,330,331,324,1,1,1,1,1,35,324,331,332,325,1,1,1,1,1,35,325,332,333,326,1,1,1,1,1,35,326,333,334,327,1,1,1,1,1,35,327,334,335,328,1,1,1,1,1,35,70,5,78,329,1,1,1,1,1,35,329,78,79,330,1,1,1,1,1,35,330,79,80,331,1,1,1,1,1,35,331,80,81,332,1,1,1,1,1,35,332,81,82,333,1,1,1,1,1,35,333,82,83,334,1,1,1,1,1,35,334,83,84,335,1,1,1,1,1,35,14,342,29,1,0,0,0,0,0,35,342,349,30,29,0,0,0,0,0,35,349,356,31,30,0,0,0,0,0,35,356,362,32,31,0,0,0,0,0,35,362,369,33,32,0,0,0,0,0,35,369,376,34,33,0,0,0,0,0,35,376,383,35,34,0,0,0,0,0,35,0,15,336,8,0,0,0,0,0,35,8,336,337,9,0,0,0,0,0,35,9,337,338,10,0,0,0,0,0,35,10,338,339,11,0,0,0,0,0,35,11,339,340,12,0,0,0,0,0,35,12,340,341,13,0,0,0,0,0,35,13,341,342,14,0,174,174,174,174,35,15,16,343,336,0,0,0,0,0,35,336,343,344,337,0,0,0,0,0,35,337,344,345,338,0,0,0,0,0,35,338,345,346,339,0,0,0,0,0,35,339,346,347,340,0,0,0,0,0,35,340,347,348,341,0,0,0,0,0,35,341,348,349,342,0,175,175,175,175,35,16,17,350,343,0,0,0,0,0,35,343,350,351,344,0,0,0,0,0,35,344,351,352,345,0,0,0,0,0,35,355,354,360,361,0,148,148,148,148,35,361,360,367,368,0,148,148,148,148,35,347,354,355,348,0,0,0,0,0,35,348,355,356,349,0,175,175,175,175,35,17,18,357,350,0,0,0,0,0,35,350,357,358,351,0,0,0,0,0,35,374,367,366,373,0,109,109,109,109,35,566,559,619,623,1,176,176,176,176,35,554,567,591,578,1,31,31,31,31,35,373,366,365,372,0,109,109,109,109,35,355,361,362,356,0,177,177,177,177,35,18,19,363,357,0,0,0,0,0,35,357,363,364,358,0,0,0,0,0,35,359,358,364,365,0,148,148,148,148,35,565,554,578,589,1,31,31,31,31,35,561,365,574,585,1,31,31,31,31,35,352,351,358,359,0,148,148,148,148,35,361,368,369,362,0,178,178,178,178,35,19,20,370,363,0,0,0,0,0,35,363,370,371,364,0,0,0,0,0,35,364,371,372,365,0,0,0,0,0,35,346,345,352,353,0,148,148,148,148,35,347,346,353,354,0,148,148,148,148,35,367,374,375,368,0,0,0,0,0,35,368,375,376,369,0,179,179,179,179,35,20,21,377,370,0,0,0,0,0,35,370,377,378,371,0,0,0,0,0,35,371,378,379,372,0,0,0,0,0,35,372,379,380,373,0,0,0,0,0,35,373,380,381,374,0,0,0,0,0,35,374,381,382,375,0,0,0,0,0,35,375,382,383,376,0,180,180,180,180,35,21,3,49,377,0,0,0,0,0,35,377,49,48,378,0,0,0,0,0,35,378,48,47,379,0,0,0,0,0,35,379,47,46,380,0,0,0,0,0,35,380,46,45,381,0,0,0,0,0,35,381,45,44,382,0,0,0,0,0,35,382,44,43,383,0,181,181,181,181,35,392,159,402,416,1,0,0,0,0,35,387,398,431,426,1,1,1,1,1,35,389,173,407,413,1,182,182,182,182,35,391,399,432,427,1,64,64,64,64,35,394,397,421,418,1,183,183,183,183,35,386,399,423,410,1,0,0,0,0,35,397,386,410,421,1,0,0,0,0,35,393,171,405,417,1,65,65,65,65,35,399,386,425,432,1,148,148,148,148,35,173,395,419,407,1,0,0,0,0,35,384,157,400,408,1,184,184,184,184,35,159,385,409,402,1,184,184,184,184,35,422,411,404,416,2,48,48,48,48,35,421,412,406,418,2,48,48,48,48,35,420,413,407,419,2,48,48,48,48,35,411,420,419,404,2,48,48,48,48,35,418,406,413,420,2,48,48,48,48,35,403,417,421,410,2,48,48,48,48,35,417,405,412,421,2,77,77,77,77,35,409,422,416,402,2,48,48,48,48,35,401,415,422,409,2,48,48,48,48,35,408,423,415,401,2,48,48,48,48,35,400,414,423,408,2,48,48,48,48,35,414,403,410,423,2,48,48,48,48,35,398,387,411,422,1,65,65,65,65,35,395,166,404,419,1,0,0,0,0,35,385,158,401,409,1,38,38,38,38,35,391,398,422,415,1,182,182,182,182,35,158,384,408,401,1,38,38,38,38,35,164,393,417,403,1,65,65,65,65,35,166,392,416,404,1,0,0,0,0,35,390,164,403,414,1,65,65,65,65,35,388,172,406,412,1,67,67,67,67,35,171,388,412,405,1,182,182,182,182,35,399,391,415,423,1,182,182,182,182,35,396,394,418,420,1,183,183,183,183,35,432,425,424,427,1,48,48,48,48,35,424,428,429,426,1,48,48,48,48,35,425,430,428,424,1,48,48,48,48,35,427,424,426,431,1,48,48,48,48,35,386,397,430,425,1,148,148,148,148,35,397,394,428,430,1,183,183,183,183,35,396,387,426,429,1,1,1,1,1,35,394,396,429,428,1,183,183,183,183,35,440,110,450,464,1,31,31,31,31,35,435,446,503,498,1,109,109,109,109,35,437,124,455,461,1,31,31,31,31,35,439,447,504,499,1,185,185,185,185,35,444,442,466,468,1,31,31,31,31,35,447,439,463,471,1,31,31,31,31,35,122,436,460,453,1,31,31,31,31,35,438,115,451,462,1,31,31,31,31,35,447,434,497,504,1,1,1,1,1,35,117,440,464,452,1,31,31,31,31,35,110,433,457,450,1,31,31,31,31,35,439,446,470,463,1,31,31,31,31,35,455,467,491,479,1,169,169,169,169,35,451,465,489,475,1,0,0,0,0,35,456,448,472,480,1,48,48,48,48,35,468,466,490,492,1,48,48,48,48,35,471,463,487,495,1,185,185,185,185,35,450,457,481,474,1,48,48,48,48,35,454,461,485,478,1,142,142,142,142,35,460,454,478,484,1,142,142,142,142,35,452,464,488,476,1,169,169,169,169,35,448,462,486,472,1,0,0,0,0,35,464,450,474,488,1,169,169,169,169,35,463,470,494,487,1,142,142,142,142,35,443,117,452,467,1,31,31,31,31,35,441,122,453,465,1,31,31,31,31,35,445,434,458,469,1,31,31,31,31,35,109,165,456,449,1,31,31,31,31,35,115,441,465,451,1,31,31,31,31,35,434,447,471,458,1,31,31,31,31,35,442,445,469,466,1,31,31,31,31,35,123,437,461,454,1,31,31,31,31,35,435,444,468,459,1,31,31,31,31,35,446,435,459,470,1,31,31,31,31,35,436,123,454,460,1,31,31,31,31,35,433,109,449,457,1,31,31,31,31,35,494,483,476,488,3,186,186,186,186,35,493,484,478,490,3,187,187,187,187,35,492,485,479,491,3,8,8,8,8,35,483,492,491,476,3,8,8,8,8,35,490,478,485,492,3,8,8,8,8,35,475,489,493,482,3,25,25,25,25,35,489,477,484,493,3,188,188,188,188,35,481,494,488,474,3,189,189,189,189,35,473,487,494,481,3,8,8,8,8,35,480,495,487,473,3,8,8,8,8,35,472,486,495,480,3,26,26,26,26,35,486,475,482,495,3,8,8,8,8,35,465,453,477,489,1,0,0,0,0,35,469,458,482,493,1,169,169,169,169,35,461,455,479,485,1,142,142,142,142,35,462,451,475,486,1,0,0,0,0,35,458,471,495,482,1,169,169,169,169,35,466,469,493,490,1,48,48,48,48,35,453,460,484,477,1,142,142,142,142,35,459,468,492,483,1,0,0,0,0,35,449,456,480,473,1,190,190,190,190,35,457,449,473,481,1,191,191,191,191,35,470,459,483,494,1,0,0,0,0,35,467,452,476,491,1,169,169,169,169,35,504,497,496,499,1,192,192,192,192,35,496,500,501,498,1,8,8,8,8,35,497,502,500,496,1,193,193,193,193,35,499,496,498,503,1,194,194,194,194,35,434,445,502,497,1,1,1,1,1,35,445,442,500,502,1,71,71,71,71,35,444,435,498,501,1,109,109,109,109,35,442,444,501,500,1,71,71,71,71,35,505,255,522,529,1,67,67,67,67,35,507,518,551,546,1,65,65,65,65,35,254,510,534,521,1,1,1,1,1,35,511,519,552,547,1,144,144,144,144,35,518,507,531,542,1,1,1,1,1,35,512,256,523,536,1,148,148,148,148,35,509,270,528,533,1,195,195,195,195,35,507,516,540,531,1,1,1,1,1,35,519,506,545,552,1,0,0,0,0,35,269,509,533,527,1,195,195,195,195,35,514,517,541,538,1,67,67,67,67,35,506,519,543,530,1,148,148,148,148,35,542,531,525,536,4,132,132,132,132,35,541,532,527,538,4,196,196,196,196,35,540,533,528,539,4,197,197,197,197,35,531,540,539,525,4,198,198,198,198,35,538,527,533,540,4,196,196,196,196,35,524,537,541,530,4,198,198,198,198,35,537,526,532,541,4,199,199,199,199,35,529,542,536,523,4,132,132,132,132,35,522,535,542,529,4,132,132,132,132,35,520,543,535,522,4,132,132,132,132,35,521,534,543,520,4,132,132,132,132,35,534,524,530,543,4,132,132,132,132,35,261,513,537,524,1,1,1,1,1,35,263,512,536,525,1,148,148,148,148,35,510,261,524,534,1,1,1,1,1,35,268,508,532,526,1,195,195,195,195,35,519,511,535,543,1,144,144,144,144,35,516,514,538,540,1,67,67,67,67,35,508,269,527,532,1,195,195,195,195,35,116,254,521,520,1,200,200,200,200,35,270,515,539,528,1,148,148,148,148,35,256,505,529,523,1,200,200,200,200,35,513,268,526,537,1,1,1,1,1,35,517,506,530,541,1,148,148,148,148,35,552,545,544,547,1,132,132,132,132,35,544,548,549,546,1,132,132,132,132,35,545,550,548,544,1,132,132,132,132,35,547,544,546,551,1,132,132,132,132,35,506,517,550,545,1,0,0,0,0,35,517,514,548,550,1,67,67,67,67,35,516,507,546,549,1,65,65,65,65,35,514,516,549,548,1,67,67,67,67,35,367,563,587,576,1,31,31,31,31,35,555,566,623,618,1,201,201,201,201,35,262,352,569,568,1,31,31,31,31,35,559,567,624,619,1,30,30,30,30,35,359,561,585,572,1,31,31,31,31,35,353,262,568,570,1,31,31,31,31,35,563,360,573,587,1,31,31,31,31,35,564,562,586,588,1,31,31,31,31,35,567,554,617,624,1,202,202,202,202,35,567,559,583,591,1,31,31,31,31,35,365,556,580,574,1,31,31,31,31,35,352,558,582,569,1,31,31,31,31,35,586,589,613,610,1,203,203,203,203,35,578,591,615,602,1,202,202,202,202,35,582,572,596,606,1,204,204,204,204,35,581,576,600,605,1,205,205,205,205,35,589,578,602,613,1,206,206,206,206,35,585,574,598,609,1,207,207,207,207,35,576,587,611,600,1,208,208,208,208,35,572,585,609,596,1,209,209,209,209,35,568,569,593,592,1,48,48,48,48,35,588,586,610,612,1,210,210,210,210,35,591,583,607,615,1,132,132,132,132,35,571,577,601,595,1,48,48,48,48,35,562,565,589,586,1,31,31,31,31,35,556,366,575,580,1,31,31,31,31,35,366,557,581,575,1,31,31,31,31,35,555,564,588,579,1,31,31,31,31,35,566,555,579,590,1,31,31,31,31,35,354,553,577,571,1,31,31,31,31,35,553,353,570,577,1,31,31,31,31,35,559,566,590,583,1,31,31,31,31,35,360,560,584,573,1,31,31,31,31,35,557,367,576,581,1,31,31,31,31,35,560,354,571,584,1,31,31,31,31,35,558,359,572,582,1,31,31,31,31,35,614,603,597,608,5,0,0,0,0,35,613,604,599,610,5,0,0,0,0,35,612,605,600,611,5,0,0,0,0,35,603,612,611,597,5,0,0,0,0,35,610,599,605,612,5,0,0,0,0,35,596,609,613,602,5,0,0,0,0,35,609,598,604,613,5,0,0,0,0,35,601,614,608,595,5,0,0,0,0,35,594,607,614,601,5,0,0,0,0,35,592,615,607,594,5,0,0,0,0,35,593,606,615,592,5,0,0,0,0,35,606,596,602,615,5,0,0,0,0,35,574,580,604,598,1,211,211,211,211,35,579,588,612,603,1,212,212,212,212,35,570,568,592,594,1,213,213,213,213,35,577,570,594,601,1,214,214,214,214,35,590,579,603,614,1,201,201,201,201,35,587,573,597,611,1,208,208,208,208,35,583,590,614,607,1,176,176,176,176,35,584,571,595,608,1,206,206,206,206,35,569,582,606,593,1,209,209,209,209,35,573,584,608,597,1,202,202,202,202,35,580,575,599,604,1,211,211,211,211,35,575,581,605,599,1,215,215,215,215,35,624,617,616,619,1,0,0,0,0,35,616,620,621,618,1,0,0,0,0,35,617,622,620,616,1,0,0,0,0,35,619,616,618,623,1,0,0,0,0,35,554,565,622,617,1,206,206,206,206,35,565,562,620,622,1,203,203,203,203,35,564,555,618,621,1,212,212,212,212,35,562,564,621,620,1,210,210,210,210,35,305,653,630,642,1,216,216,216,216,35,658,646,637,625,1,217,217,217,217,35,655,661,665,628,1,218,218,218,218,35,317,655,628,641,1,219,219,219,219,35,636,634,642,630,6,1,1,1,1,35,637,627,667,633,6,1,1,1,1,35,639,629,666,311,6,1,1,1,1,35,627,636,630,667,6,1,1,1,1,35,311,666,634,636,6,1,1,1,1,35,631,637,633,643,6,1,1,1,1,35,668,625,637,631,6,1,1,1,1,35,632,638,625,668,6,1,1,1,1,35,641,628,638,632,6,1,1,1,1,35,628,665,626,638,6,1,1,1,1,35,665,635,639,626,6,1,1,1,1,35,635,640,629,639,6,1,1,1,1,35,644,657,626,639,1,220,220,220,220,35,653,663,667,630,1,216,216,216,216,35,656,646,671,673,1,173,173,173,173,35,647,659,311,636,1,172,172,172,172,35,659,644,639,311,1,221,221,221,221,35,651,317,641,632,1,51,51,51,51,35,646,658,675,671,1,222,222,222,222,35,661,648,635,665,1,218,218,218,218,35,649,305,642,634,1,223,223,223,223,35,663,650,633,667,1,216,216,216,216,35,647,656,673,672,1,224,224,224,224,35,645,658,625,638,1,225,225,225,225,35,303,652,631,643,1,226,226,226,226,35,659,647,672,676,1,227,227,227,227,35,319,654,629,640,1,228,228,228,228,35,654,662,666,629,1,170,170,170,170,35,650,303,643,633,1,216,216,216,216,35,657,645,638,626,1,220,220,220,220,35,652,664,668,631,1,172,172,172,172,35,656,647,636,627,1,224,224,224,224,35,674,669,676,677,1,1,1,1,1,35,675,677,673,671,1,1,1,1,1,35,677,676,672,673,1,1,1,1,1,35,670,674,677,675,1,1,1,1,1,35,658,645,670,675,1,225,225,225,225,35,645,657,674,670,1,220,220,220,220,35,644,659,676,669,1,229,229,229,229,35,657,644,669,674,1,220,220,220,220,35,206,683,707,693,1,1,1,1,1,35,680,691,724,719,1,169,169,169,169,35,680,689,713,704,1,1,1,1,1,35,684,692,725,720,1,230,230,230,230,35,220,682,706,699,1,162,162,162,162,35,685,208,695,709,1,109,109,109,109,35,682,221,700,706,1,162,162,162,162,35,687,690,714,711,1,231,231,231,231,35,692,679,718,725,1,0,0,0,0,35,679,692,716,703,1,109,109,109,109,35,690,679,703,714,1,109,109,109,109,35,686,219,698,710,1,1,1,1,1,35,715,704,697,709,7,93,93,93,93,35,714,705,699,711,7,232,232,232,232,35,713,706,700,712,7,233,233,233,233,35,704,713,712,697,7,233,233,233,233,35,711,699,706,713,7,233,233,233,233,35,696,710,714,703,7,234,234,234,234,35,710,698,705,714,7,233,233,233,233,35,702,715,709,695,7,93,93,93,93,35,694,708,715,702,7,93,93,93,93,35,701,716,708,694,7,93,93,93,93,35,693,707,716,701,7,93,93,93,93,35,707,696,703,716,7,93,93,93,93,35,684,691,715,708,1,235,235,235,235,35,207,660,701,694,1,231,231,231,231,35,213,686,710,696,1,1,1,1,1,35,214,685,709,697,1,109,109,109,109,35,683,213,696,707,1,1,1,1,1,35,681,220,699,705,1,236,236,236,236,35,219,681,705,698,1,162,162,162,162,35,692,684,708,716,1,236,236,236,236,35,689,687,711,713,1,50,50,50,50,35,208,678,702,695,1,50,50,50,50,35,660,206,693,701,1,50,50,50,50,35,221,688,712,700,1,109,109,109,109,35,725,718,717,720,1,93,93,93,93,35,717,721,722,719,1,93,93,93,93,35,718,723,721,717,1,93,93,93,93,35,720,717,719,724,1,93,93,93,93,35,679,690,723,718,1,0,0,0,0,35,690,687,721,723,1,237,237,237,237,35,689,680,719,722,1,169,169,169,169,35,687,689,722,721,1,238,238,238,238]
}